[
  {
    "id": "458",
    "title": "Poor Pigs",
    "date": "2025-11-10"
  },
  {
    "id": "330",
    "title": "Patching Array",
    "date": "2025-11-10"
  },
  {
    "id": "280",
    "title": "Wiggle Sort",
    "date": "2025-11-10"
  },
  {
    "id": "432",
    "title": "All O`one Data Structure",
    "date": "2025-11-10"
  },
  {
    "id": "99",
    "title": "Recover Binary Search Tree",
    "date": "2025-11-10"
  },
  {
    "id": "403",
    "title": "Frog Jump",
    "date": "2025-11-10"
  },
  {
    "id": "238",
    "title": "Product of Array Except Self",
    "date": "2025-11-10"
  },
  {
    "id": "403",
    "title": "Frog Jump",
    "date": "2025-11-10"
  },
  {
    "id": "139",
    "title": "Word Break",
    "date": "2025-11-10"
  },
  {
    "id": "138",
    "title": "Copy List with Random Pointer",
    "date": "2025-11-10"
  }
]